video_organise.py
video_organise-1.0.1.dist-info/METADATA
video_organise-1.0.1.dist-info/WHEEL
video_organise-1.0.1.dist-info/entry_points.txt
video_organise-1.0.1.dist-info/top_level.txt
video_organise-1.0.1.dist-info/RECORD
