Metadata-Version: 2.4
Name: video-organise
Version: 1.0.1
Summary: CLI tool to organize files into date-based folders
Author-email: Tushar Pokle <tushar.pokle@gmail.com>
Project-URL: Homepage, https://github.com/pokle/video-organise
Requires-Python: >=3.12
Requires-Dist: typer>=0.21.0
